README.md
setup.py
lamatok/__init__.py
lamatok/__version__.py
lamatok/api.py
lamatok/asyncapi.py
lamatok/base.py
lamatok.egg-info/PKG-INFO
lamatok.egg-info/SOURCES.txt
lamatok.egg-info/dependency_links.txt
lamatok.egg-info/requires.txt
lamatok.egg-info/top_level.txt